k2j/__init__.py
k2j/k2j.py
k2j/k2j_test.py
k2j-0.1.0.dist-info/LICENSE
k2j-0.1.0.dist-info/METADATA
k2j-0.1.0.dist-info/WHEEL
k2j-0.1.0.dist-info/RECORD
