Metadata-Version: 2.1
Name: k2j
Version: 0.1.0
Summary: 
License: MIT
Author: tanikawa04
Author-email: tanikawa04@gmail.com
Requires-Python: >=3.8,<4.0
Classifier: License :: OSI Approved :: MIT License
Classifier: Programming Language :: Python :: 3
Classifier: Programming Language :: Python :: 3.8
Classifier: Programming Language :: Python :: 3.9
Classifier: Programming Language :: Python :: 3.10
Classifier: Programming Language :: Python :: 3.11
Provides-Extra: fugashi
Requires-Dist: fugashi[unidic] (>=1.2.1,<2.0.0) ; extra == "fugashi"
